{
  "cloudProvider": {
    "cloudProviderId": "",
    "cloudProviderType": "KUBERNETES_CLUSTER",
    "k8sCloudProvider": {
      "name": "-- replace with actual value --",


      "skipValidation": false,
      "clusterDetailsType": "MANUAL_CLUSTER_DETAILS",
      "manualClusterDetails": {
        "masterUrl": "-- replace with actual value --",

        "type":"SERVICE_ACCOUNT_TOKEN",
        "serviceAccountToken": {
          "serviceAccountTokenSecretId": "-- replace with actual value --"
        }
      }
    }
  }
}